LICENSE.txt
MANIFEST.in
README.md
setup.cfg
setup.py
versioneer.py
smallscheme/__init__.py
smallscheme/_version.py
smallscheme/builtin.py
smallscheme/dtypes.py
smallscheme/env.py
smallscheme/main.py
smallscheme/parse.py
smallscheme/scheme.py
smallscheme/test_env.py
smallscheme/test_parse.py
smallscheme/test_scheme.py
smallscheme/test_util.py
smallscheme.egg-info/PKG-INFO
smallscheme.egg-info/SOURCES.txt
smallscheme.egg-info/dependency_links.txt
smallscheme.egg-info/entry_points.txt
smallscheme.egg-info/requires.txt
smallscheme.egg-info/top_level.txt