Metadata-Version: 2.1
Name: smallscheme
Version: 0.0.17
Summary: A small Scheme implementation, whose aim is to provide enough functionality to be used to run examples and work problems in SICP
Home-page: https://github.com/eigenhombre/smallscheme
Author: John Jacobsen
Author-email: eigenhombre@gmail.com
License: MIT
Keywords: lisp sicp scheme
Classifier: Development Status :: 3 - Alpha
Classifier: License :: OSI Approved :: MIT License
License-File: LICENSE.txt
